statsuite_lib/__init__.py
statsuite_lib/auth/__init__.py
statsuite_lib/auth/auth.py
statsuite_lib/config/__init__.py
statsuite_lib/config/config.py
statsuite_lib/config/models.py
statsuite_lib/keycloak/__init__.py
statsuite_lib/keycloak/keycloak.py
statsuite_lib/nsi/__init__.py
statsuite_lib/nsi/nsi.py
statsuite_lib/sfs/__init__.py
statsuite_lib/sfs/models.py
statsuite_lib/sfs/sfs.py
statsuite_lib/transfer/__init__.py
statsuite_lib/transfer/transfer.py
statsuite_lib-0.2.4.dist-info/METADATA
statsuite_lib-0.2.4.dist-info/WHEEL
statsuite_lib-0.2.4.dist-info/RECORD
